personal_man/__init__.py
personal_man/cli.py
personal_man/controllers/__init__.py
personal_man/controllers/search_controller.py
personal_man/controllers/show_controller.py
personal_man/core/__init__.py
personal_man/core/exceptions.py
personal_man/core/version.py
personal_man/output.py
personal_man/search.py
personal_man/settings.py
personal_man/show.py
personal_man-1.1.1.dist-info/entry_points.txt
personal_man-1.1.1.dist-info/LICENSE
personal_man-1.1.1.dist-info/WHEEL
personal_man-1.1.1.dist-info/METADATA
personal_man-1.1.1.dist-info/RECORD
