Metadata-Version: 2.1
Name: personal-man
Version: 1.1.1
Summary: Personal Manpages (pman)
Home-page: https://github.com/kyleking/personal_man
License: MIT
Author: Kyle King
Author-email: dev.act.kyle@gmail.com
Requires-Python: >=3.10.5,<4.0.0
Classifier: Development Status :: 4 - Beta
Classifier: License :: OSI Approved :: MIT License
Classifier: Operating System :: OS Independent
Classifier: Programming Language :: Python :: 3
Classifier: Programming Language :: Python :: 3.11
Classifier: Programming Language :: Python :: 3.10
Requires-Dist: beartype (>=0.11.0)
Requires-Dist: cement (>=3.0.8)
Requires-Dist: loguru (>=0.6.0)
Requires-Dist: pydantic (>=1.9.1)
Requires-Dist: questionary (>=1.10.0)
Requires-Dist: rich (>=12.5.1)
Project-URL: Bug Tracker, https://github.com/kyleking/personal_man/issues
Project-URL: Changelog, https://github.com/kyleking/personal_man/blob/main/docs/docs/CHANGELOG.md
Project-URL: Documentation, https://github.com/kyleking/personal_man/docs
Project-URL: Repository, https://github.com/kyleking/personal_man
